friendly_hash/__init__.py
friendly_hash/friendly_hash.py
friendly_hash/version.py
tests/__init__.py
tests/test_human_hash.py
friendly_hash-0.1.1.dist-info/LICENSE
friendly_hash-0.1.1.dist-info/METADATA
friendly_hash-0.1.1.dist-info/WHEEL
friendly_hash-0.1.1.dist-info/entry_points.txt
friendly_hash-0.1.1.dist-info/top_level.txt
friendly_hash-0.1.1.dist-info/RECORD
