Metadata-Version: 2.1
Name: friendly-hash
Version: 0.1.1
Summary: A tool to rename files with human-readable hashes
Home-page: https://github.com/HTLife/friendly_hash
Author: JackyLiu
Author-email: jjkka132@gmail.com
License: UNKNOWN
Platform: UNKNOWN
Classifier: Programming Language :: Python :: 3
Classifier: License :: OSI Approved :: MIT License
Classifier: Operating System :: OS Independent
Requires-Python: >=3.6
License-File: LICENSE
Requires-Dist: codenamize (>=1.2.3)
